topsis/102003403.py
topsis/__init__.py
Topsis_Ikshit_102003403-1.1.3.dist-info/LICENSE.txt
Topsis_Ikshit_102003403-1.1.3.dist-info/METADATA
Topsis_Ikshit_102003403-1.1.3.dist-info/WHEEL
Topsis_Ikshit_102003403-1.1.3.dist-info/entry_points.txt
Topsis_Ikshit_102003403-1.1.3.dist-info/top_level.txt
Topsis_Ikshit_102003403-1.1.3.dist-info/RECORD
